lockman/__init__.py
lockman-0.0.1.dist-info/LICENSE
lockman-0.0.1.dist-info/METADATA
lockman-0.0.1.dist-info/WHEEL
lockman-0.0.1.dist-info/top_level.txt
lockman-0.0.1.dist-info/RECORD
