Metadata-Version: 2.1
Name: lockman
Version: 0.0.1
Summary: A simple library for managing mutexes across processes and computers.
Maintainer-email: Nadav Tasher <hey@nadav.app>
License: MIT License
Project-URL: Homepage, https://github.com/NadavTasher/LockMan
Keywords: database,filesystem
Classifier: License :: OSI Approved :: MIT License
Classifier: Programming Language :: Python
Classifier: Programming Language :: Python :: 3
License-File: LICENSE
